TCRAPI/__init__.py
TCRAPI/__main__.py
TCRAPI/api.py
TCRAPI/auth.py
TCRAPI/config.py
TCRAPI/enums.py
TCRAPI/models.py
TCRAPI/utils.py
TCRAPI/getgriddata/CustomerContacts.py
TCRAPI/getgriddata/CustomerInvoices.py
TCRAPI/getgriddata/CustomerJobs.py
TCRAPI/getgriddata/Customers.py
TCRAPI/getgriddata/DriverSchedule.py
TCRAPI/getgriddata/Drivers.py
TCRAPI/getgriddata/InvoiceDetails.py
TCRAPI/getgriddata/Invoices.py
TCRAPI/getgriddata/JobInvoices.py
TCRAPI/getgriddata/JobTCPs.py
TCRAPI/getgriddata/JobTickets.py
TCRAPI/getgriddata/Jobs.py
TCRAPI/getgriddata/LaborTickets.py
TCRAPI/getgriddata/LineItems.py
TCRAPI/getgriddata/PriceListItems.py
TCRAPI/getgriddata/PriceLists.py
TCRAPI/getgriddata/TicketItems.py
TCRAPI/getgriddata/TicketLabor.py
TCRAPI/getgriddata/TicketReturnSigns.py
TCRAPI/getgriddata/TicketSigns.py
TCRAPI/getgriddata/TicketTCPs.py
TCRAPI/getgriddata/Tickets.py
TCRAPI/getgriddata/__init__.py
TCRAPI-0.1.2.dist-info/LICENSE
TCRAPI-0.1.2.dist-info/METADATA
TCRAPI-0.1.2.dist-info/WHEEL
TCRAPI-0.1.2.dist-info/top_level.txt
TCRAPI-0.1.2.dist-info/RECORD
